[{"__symbolic":"module","version":3,"metadata":{"createRefs":{"__symbolic":"function","parameters":[],"value":{"__symbolic":"new","expression":{"__symbolic":"reference","name":"Refs_"}}},"Refs_":{"__symbolic":"class","members":{"createComponentFactory":[{"__symbolic":"method"}],"createViewRef":[{"__symbolic":"method"}],"createViewContainerRef":[{"__symbolic":"method"}],"createTemplateRef":[{"__symbolic":"method"}],"createInjector":[{"__symbolic":"method"}],"createDebugContext":[{"__symbolic":"method"}]}}}},{"__symbolic":"module","version":1,"metadata":{"createRefs":{"__symbolic":"function","parameters":[],"value":{"__symbolic":"new","expression":{"__symbolic":"reference","name":"Refs_"}}},"Refs_":{"__symbolic":"class","members":{"createComponentFactory":[{"__symbolic":"method"}],"createViewRef":[{"__symbolic":"method"}],"createViewContainerRef":[{"__symbolic":"method"}],"createTemplateRef":[{"__symbolic":"method"}],"createInjector":[{"__symbolic":"method"}],"createDebugContext":[{"__symbolic":"method"}]}}}}]